cla.sv
module cla_4b (
	input logic CI,
	input logic [3:0] A, B,
	output logic CO,
	output logic [3:0] S
);
	logic [2:0] C;
	logic [3:0] g, p;

	// Compute p's
	assign p[0] = A[0] ^ B[0];
	assign p[1] = A[1] ^ B[1];
	assign p[2] = A[2] ^ B[2];
	assign p[3] = A[3] ^ B[3];

	// Compute g's
	assign g[0] = A[0] & B[0];
	assign g[1] = A[1] & B[1];
	assign g[2] = A[2] & B[2];
	assign g[3] = A[3] & B[3];

	// Compute the all the carries
	assign C[0] = g[0] | (p[0] & CI);
	assign C[1] = g[1] | (p[1] & g[0]) | (p[1] & p[0] & CI);
	assign C[2] = g[2] | (p[2] & g[1]) | (p[2] & p[1] & g[0]) | (p[2] & p[1] & p[0] & CI);
	assign CO = g[3] | (p[3] & g[2]) | (p[3] & p[2] & g[1]) | (p[3] & p[2] & p[1] & g[0]) | (p[3] & p[2] & p[1] & p[0] & CI);

	// Compute the sum
	assign S[0] = p[0] ^ CI;
	assign S[1] = p[1] ^ C[0];
	assign S[2] = p[2] ^ C[1];
	assign S[3] = p[3] ^ C[2];

endmodule

cla_tb.sv
module tb ();
    logic [3:0] tb_X;
    logic [3:0] tb_Y;
    logic [3:0] tb_S;
    logic tb_CO;

    // instance of DUT
    cla_4b test (.CI(1'b0), .A(tb_X), .B(tb_Y), .CO(tb_CO), .S(tb_S));

    initial begin
        
        $monitor ("A=%d, B=%d, CO=%d, S=%d", tb_X, tb_Y, tb_CO, tb_S);

        #1
        tb_X = 0;
        tb_Y = 0;

        #1
        tb_X = 1;
        tb_Y = 0;

        #1
        tb_X = 2;
        tb_Y = 1;

        #1
        tb_X = 2;
        tb_Y = 3;

        #1
        tb_X = 3;
        tb_Y = 3;

        #1
        tb_X = 7;
        tb_Y = 3;

        #1
        tb_X = 3;
        tb_Y = 12;

        #1
        tb_X = 10;
        tb_Y = 0;
        
        #1
        tb_X = 3;
        tb_Y = 4;

        #1
        tb_X = 14;
        tb_Y = 1;

        #1
        tb_X = 3;
        tb_Y = 6;

        #1
        tb_X = 7;
        tb_Y = 2;

        #1
        tb_X = 1;
        tb_Y = 5;

        #1
        tb_X = 6;
        tb_Y = 4;

        #1
        tb_X = 15;
        tb_Y = 15;

        #1
        $display("TEST COMPLETE");
        $finish();
    end

    // To dump signals to waveform
    initial begin
        $dumpfile("dump.vcd");
        $dumpvars; 
    end

endmodule

dump.vcd
$date
	Tue Dec 27 03:46:17 2022
$end
$version
	Icarus Verilog
$end
$timescale
	1s
$end
$scope module tb $end
$var wire 4 ! tb_S [3:0] $end
$var wire 1 " tb_CO $end
$var reg 4 # tb_X [3:0] $end
$var reg 4 $ tb_Y [3:0] $end
$scope module test $end
$var wire 4 % A [3:0] $end
$var wire 4 & B [3:0] $end
$var wire 1 ' CI $end
$var wire 1 " CO $end
$var wire 4 ( p [3:0] $end
$var wire 4 ) g [3:0] $end
$var wire 4 * S [3:0] $end
$var wire 3 + C [2:0] $end
$upscope $end
$upscope $end
$enddefinitions $end
#0
$dumpvars
bx +
bx *
bx )
bx (
0'
bx &
bx %
bx $
bx #
x"
bx !
$end
#1
0"
b0 !
b0 *
b0 +
b0 (
b0 )
b0 $
b0 &
b0 #
b0 %
#2
b1 !
b1 *
b1 (
b1 #
b1 %
#3
b11 !
b11 *
b11 (
b1 $
b1 &
b10 #
b10 %
#4
b10 +
b101 !
b101 *
b1 (
b10 )
b11 $
b11 &
#5
b110 !
b110 *
b11 +
b0 (
b11 )
b11 #
b11 %
#6
b111 +
b1010 !
b1010 *
b100 (
b111 #
b111 %
#7
b1111 !
b1111 *
b0 +
b1111 (
b0 )
b1100 $
b1100 &
b11 #
b11 %
#8
b1010 !
b1010 *
b1010 (
b0 $
b0 &
b1010 #
b1010 %
#9
b111 !
b111 *
b111 (
b100 $
b100 &
b11 #
b11 %
#10
b1111 !
b1111 *
b1111 (
b1 $
b1 &
b1110 #
b1110 %
#11
b110 +
b1001 !
b1001 *
b10 )
b101 (
b110 $
b110 &
b11 #
b11 %
#12
b10 $
b10 &
b111 #
b111 %
#13
b110 !
b110 *
b1 +
b100 (
b1 )
b101 $
b101 &
b1 #
b1 %
#14
b1010 !
b1010 *
b100 +
b10 (
b100 )
b100 $
b100 &
b110 #
b110 %
#15
1"
b1110 !
b1110 *
b111 +
b0 (
b1111 )
b1111 $
b1111 &
b1111 #
b1111 %
