cla.sv
module com_pg (
	input logic [15:0] A, B,
	output logic [15:0] p, g
);
	// Compute p's
	assign p[0] = A[0] ^ B[0];
	assign p[1] = A[1] ^ B[1];
	assign p[2] = A[2] ^ B[2];
	assign p[3] = A[3] ^ B[3];
	assign p[4] = A[4] ^ B[4];
	assign p[5] = A[5] ^ B[5];
	assign p[6] = A[6] ^ B[6];
	assign p[7] = A[7] ^ B[7];
	assign p[8] = A[8] ^ B[8];
	assign p[9] = A[9] ^ B[9];
	assign p[10] = A[10] ^ B[10];
	assign p[11] = A[11] ^ B[11];
	assign p[12] = A[12] ^ B[12];
	assign p[13] = A[13] ^ B[13];
	assign p[14] = A[14] ^ B[14];
	assign p[15] = A[15] ^ B[15];

	// Compute g's
	assign g[0] = A[0] & B[0];
	assign g[1] = A[1] & B[1];
	assign g[2] = A[2] & B[2];
	assign g[3] = A[3] & B[3];
	assign g[4] = A[4] & B[4];
	assign g[5] = A[5] & B[5];
	assign g[6] = A[6] & B[6];
	assign g[7] = A[7] & B[7];
	assign g[8] = A[8] & B[8];
	assign g[9] = A[9] & B[9];
	assign g[10] = A[10] & B[10];
	assign g[11] = A[11] & B[11];
	assign g[12] = A[12] & B[12];
	assign g[13] = A[13] & B[13];
	assign g[14] = A[14] & B[14];
	assign g[15] = A[15] & B[15];

endmodule

module cla_4b (
	input logic CI,
	input logic [3:0] p, g,
	output logic [3:0] S
);
	logic [2:0] C;

	// Compute the all the carries
	assign C[0] = g[0] | (p[0] & CI);
	assign C[1] = g[1] | (p[1] & g[0]) | (&p[1:0] & CI);
	assign C[2] = g[2] | (p[2] & g[1]) | (&p[2:1] & g[0]) | (&p[2:0] & CI);

	// Compute the sum
	assign S[0] = p[0] ^ CI;
	assign S[1] = p[1] ^ C[0];
	assign S[2] = p[2] ^ C[1];
	assign S[3] = p[3] ^ C[2];

endmodule

module cla_16b (
	input logic CI,
	input logic [15:0] A, B,
	output logic CO,
	output logic [15:0] S
);
	logic [2:0] C;
	logic [3:0] P, G;
	logic [15:0] p, g, buff, nB;

	// Invert
	assign buff = {16{CI}};
	assign nB = B ^ buff;

	// Compute the p's and g's
	com_pg pg (.A(A), .B(nB), .p(p), .g(g));

	// Compute P's
	assign P[0] = &p[3:0];
	assign P[1] = &p[7:4];
	assign P[2] = &p[11:8];
	assign P[3] = &p[15:12];

	// Compute G's
	assign G[0] = g[3] | (p[3] & g[2]) | (&p[3:2] & g[1]) | (&p[3:1] & g[0]);
	assign G[1] = g[7] | (p[7] & g[6]) | (&p[7:6] & g[5]) | (&p[7:5] & g[4]);
	assign G[2] = g[11] | (p[11] & g[10]) | (&p[11:10] & g[9]) | (&p[11:9] & g[8]);
	assign G[3] = g[15] | (p[15] & g[14]) | (&p[15:14] & g[13]) | (&p[15:13] & g[12]);

	// Compute the carries
	assign C[0] = G[0] | (P[0] & CI);
	assign C[1] = G[1] | (P[1] & G[0]) | (&P[1:0] & CI);
	assign C[2] = G[2] | (P[2] & G[1]) | (&P[2:1] & G[0]) | (&P[2:0] & CI);
	assign CO = G[3] | (P[3] & G[2]) | (&P[3:2] & G[1]) | (&P[3:1] & G[0]) | (&P[3:0] & CI);

	// Compute the sums
	cla_4b s1 (.CI(CI), .p(p[3:0]), .g(g[3:0]), .S(S[3:0]));
	cla_4b s2 (.CI(C[0]), .p(p[7:4]), .g(g[7:4]), .S(S[7:4]));
	cla_4b s3 (.CI(C[1]), .p(p[11:8]), .g(g[11:8]), .S(S[11:8]));
	cla_4b s4 (.CI(C[2]), .p(p[15:12]), .g(g[15:12]), .S(S[15:12]));

endmodule

cla_tb.sv
module tb ();
    logic tb_CO, tb_CI;
    logic signed [15:0] tb_X, tb_Y, tb_S;

    // instance of DUT
    cla_16b test (.CI(tb_CI), .A(tb_X), .B(tb_Y), .CO(tb_CO), .S(tb_S));

    initial begin
        
        $monitor ("A=%d, B=%d, CI=%d, CO=%d, S=%d", tb_X, tb_Y, tb_CI, tb_CO, tb_S);

        #1
        tb_X = 0;
        tb_Y = 0;
        tb_CI = 0;

        #1
        tb_X = 1;
        tb_Y = 1;
        tb_CI = 0;

        #1
        tb_X = 1;
        tb_Y = 1;
        tb_CI = 1;

        #1
        tb_X = 0;
        tb_Y = 0;
        tb_CI = 1;

        #1
        tb_X = 32767;
        tb_Y = 32767;
        tb_CI = 1;

        #1
        tb_X = 30000;
        tb_Y = 2767;
        tb_CI = 0;

        #1
        tb_X = 54;
        tb_Y = 46;
        tb_CI = 0;

        #1
        tb_X = 200;
        tb_Y = 100;
        tb_CI = 1;

        #1
        tb_X = 444;
        tb_Y = 666;
        tb_CI = 0;

        #1
        tb_X = 444;
        tb_Y = 666;
        tb_CI = 1;

        #1
        tb_X = 32767;
        tb_Y = 32767;
        tb_CI = 0;

        #1
        $display("TEST COMPLETE");
        $finish();
    end

    // To dump signals to waveform
    initial begin
        $dumpfile("dump.vcd");
        $dumpvars; 
    end

endmodule

dump.vcd
$date
	Tue Dec 27 17:31:08 2022
$end
$version
	Icarus Verilog
$end
$timescale
	1s
$end
$scope module tb $end
$var wire 16 ! tb_S [15:0] $end
$var wire 1 " tb_CO $end
$var reg 1 # tb_CI $end
$var reg 16 $ tb_X [15:0] $end
$var reg 16 % tb_Y [15:0] $end
$scope module test $end
$var wire 16 & A [15:0] $end
$var wire 16 ' B [15:0] $end
$var wire 1 # CI $end
$var wire 1 " CO $end
$var wire 16 ( nB [15:0] $end
$var wire 16 ) p [15:0] $end
$var wire 16 * g [15:0] $end
$var wire 16 + buff [15:0] $end
$var wire 16 , S [15:0] $end
$var wire 4 - P [3:0] $end
$var wire 4 . G [3:0] $end
$var wire 3 / C [2:0] $end
$scope module pg $end
$var wire 16 0 A [15:0] $end
$var wire 16 1 B [15:0] $end
$var wire 16 2 p [15:0] $end
$var wire 16 3 g [15:0] $end
$upscope $end
$scope module s1 $end
$var wire 1 # CI $end
$var wire 4 4 g [3:0] $end
$var wire 4 5 p [3:0] $end
$var wire 4 6 S [3:0] $end
$var wire 3 7 C [2:0] $end
$upscope $end
$scope module s2 $end
$var wire 1 8 CI $end
$var wire 4 9 g [3:0] $end
$var wire 4 : p [3:0] $end
$var wire 4 ; S [3:0] $end
$var wire 3 < C [2:0] $end
$upscope $end
$scope module s3 $end
$var wire 1 = CI $end
$var wire 4 > g [3:0] $end
$var wire 4 ? p [3:0] $end
$var wire 4 @ S [3:0] $end
$var wire 3 A C [2:0] $end
$upscope $end
$scope module s4 $end
$var wire 1 B CI $end
$var wire 4 C g [3:0] $end
$var wire 4 D p [3:0] $end
$var wire 4 E S [3:0] $end
$var wire 3 F C [2:0] $end
$upscope $end
$upscope $end
$upscope $end
$enddefinitions $end
#0
$dumpvars
bx F
bx E
bx D
bx C
xB
bx A
bx @
bx ?
bx >
x=
bx <
bx ;
bx :
bx 9
x8
bx 7
bx 6
bx 5
bx 4
bx 3
bx 2
bx 1
bx 0
bx /
bx .
bx -
bx ,
bx +
bx *
bx )
bx (
bx '
bx &
bx %
bx $
x#
x"
bx !
$end
#1
0B
0"
0=
b0 ;
b0 @
b0 E
08
b0 /
b0 <
b0 A
b0 F
b0 !
b0 ,
b0 6
b0 7
b0 .
b0 5
b0 :
b0 ?
b0 D
b0 -
b0 )
b0 2
b0 4
b0 9
b0 >
b0 C
b0 *
b0 3
b0 (
b0 1
b0 +
0#
b0 %
b0 '
b0 $
b0 &
b0 0
#2
b1 7
b10 !
b10 ,
b10 6
b1 4
b1 *
b1 3
b0 5
b0 )
b0 2
b1 (
b1 1
b1 %
b1 '
b1 $
b1 &
b1 0
#3
b111 <
b111 A
b111 F
18
1=
1B
b111 /
1"
b0 ;
b0 @
b0 E
b111 7
b1111 5
b1111 :
b1111 ?
b1111 D
b1111 -
b0 4
b1111111111111111 )
b1111111111111111 2
b0 *
b0 3
b1111111111111110 (
b1111111111111110 1
b0 !
b0 ,
b0 6
b1111111111111111 +
1#
#4
b111 <
b111 A
b111 F
b0 ;
b0 @
b0 E
18
1=
1B
b111 7
b111 /
b0 !
b0 ,
b0 6
1"
b1111 5
b1111 -
b1111111111111111 )
b1111111111111111 2
b1111111111111111 (
b1111111111111111 1
b0 %
b0 '
b0 $
b0 &
b0 0
#5
18
1=
1B
b111 7
b111 <
b111 A
b111 /
b111 F
b0 .
b0 6
b0 ;
b0 @
b0 !
b0 ,
b0 E
1"
b1111 5
b1111 :
b1111 ?
b1111 D
b1111 -
b0 4
b0 9
b0 >
b0 C
b1111111111111111 )
b1111111111111111 2
b0 *
b0 3
b1000000000000000 (
b1000000000000000 1
b111111111111111 %
b111111111111111 '
b111111111111111 $
b111111111111111 &
b111111111111111 0
#6
b0 <
b0 A
b0 F
b1111 ;
b1111 @
b111 E
b111 D
08
0=
0B
b1111 5
b1111 :
b1111 ?
b111 -
b0 /
0"
b0 7
b111111111111111 )
b111111111111111 2
b111111111111111 !
b111111111111111 ,
b1111 6
b101011001111 (
b101011001111 1
b0 +
0#
b101011001111 %
b101011001111 '
b111010100110000 $
b111010100110000 &
b111010100110000 0
#7
18
b1 /
b11 <
b1 .
b110 ;
b110 7
b100 6
b0 @
b1100100 !
b1100100 ,
b0 E
b1 :
b10 9
b1000 5
b0 ?
b0 -
b0 D
b110 4
b11000 )
b11000 2
b100110 *
b100110 3
b101110 (
b101110 1
b101110 %
b101110 '
b110110 $
b110110 &
b110110 0
#8
b111 F
b111 A
1B
1"
1=
b111 /
b11 .
b0 @
b0 E
b11 7
b1 <
b110 ;
b1111 ?
b1111 D
b1100 -
b11 5
b101 :
b1000 4
b1000 9
b1111111101010011 )
b1111111101010011 2
b10001000 *
b10001000 3
b1100100 !
b1100100 ,
b100 6
b1111111110011011 (
b1111111110011011 1
b1111111111111111 +
1#
b1100100 %
b1100100 '
b11001000 $
b11001000 &
b11001000 0
#9
0B
b11 /
0"
b0 F
b11 <
b0 E
b11 A
b101 ;
b100 @
b11 .
b0 D
b110 5
b10 :
b11 ?
b0 -
b1001 9
b0 >
b0 7
b1100100110 )
b1100100110 2
b10011000 *
b10011000 3
b10001010110 !
b10001010110 ,
b110 6
b1010011010 (
b1010011010 1
b0 +
0#
b1010011010 %
b1010011010 '
b110111100 $
b110111100 &
b110111100 0
#10
18
b11 /
b101 7
b1 A
b11 .
b10 ;
b1111 @
b1111 E
b111 <
b1001 5
b1101 :
b1100 ?
b1111 D
b1000 -
b100 4
b10 9
b1 >
b1111110011011001 )
b1111110011011001 2
b100100100 *
b100100100 3
b1111110101100101 (
b1111110101100101 1
b1111111100100010 !
b1111111100100010 ,
b10 6
b1111111111111111 +
1#
#11
0"
1B
b111 /
b111 A
b111 .
b1111 ;
b1111 @
b1111 E
b111 F
b0 5
b0 :
b0 ?
b0 D
b0 -
b1111 4
b1111 9
b1111 >
b111 C
b111 7
b0 )
b0 2
b111111111111111 *
b111111111111111 3
b1111111111111110 !
b1111111111111110 ,
b1110 6
b111111111111111 (
b111111111111111 1
b0 +
0#
b111111111111111 %
b111111111111111 '
b111111111111111 $
b111111111111111 &
b111111111111111 0
