cla.sv
module com_pg (
	input logic [15:0] A, B,
	output logic [15:0] p, g
);
	// Compute p's
	assign p[0] = A[0] ^ B[0];
	assign p[1] = A[1] ^ B[1];
	assign p[2] = A[2] ^ B[2];
	assign p[3] = A[3] ^ B[3];
	assign p[4] = A[4] ^ B[4];
	assign p[5] = A[5] ^ B[5];
	assign p[6] = A[6] ^ B[6];
	assign p[7] = A[7] ^ B[7];
	assign p[8] = A[8] ^ B[8];
	assign p[9] = A[9] ^ B[9];
	assign p[10] = A[10] ^ B[10];
	assign p[11] = A[11] ^ B[11];
	assign p[12] = A[12] ^ B[12];
	assign p[13] = A[13] ^ B[13];
	assign p[14] = A[14] ^ B[14];
	assign p[15] = A[15] ^ B[15];

	// Compute g's
	assign g[0] = A[0] & B[0];
	assign g[1] = A[1] & B[1];
	assign g[2] = A[2] & B[2];
	assign g[3] = A[3] & B[3];
	assign g[4] = A[4] & B[4];
	assign g[5] = A[5] & B[5];
	assign g[6] = A[6] & B[6];
	assign g[7] = A[7] & B[7];
	assign g[8] = A[8] & B[8];
	assign g[9] = A[9] & B[9];
	assign g[10] = A[10] & B[10];
	assign g[11] = A[11] & B[11];
	assign g[12] = A[12] & B[12];
	assign g[13] = A[13] & B[13];
	assign g[14] = A[14] & B[14];
	assign g[15] = A[15] & B[15];

endmodule

module cla_4b (
	input logic CI,
	input logic [3:0] p, g,
	output logic [3:0] S
);
	logic [2:0] C;

	// Compute the all the carries
	assign C[0] = g[0] | (p[0] & CI);
	assign C[1] = g[1] | (p[1] & g[0]) | (&p[1:0] & CI);
	assign C[2] = g[2] | (p[2] & g[1]) | (&p[2:1] & g[0]) | (&p[2:0] & CI);

	// Compute the sum
	assign S[0] = p[0] ^ CI;
	assign S[1] = p[1] ^ C[0];
	assign S[2] = p[2] ^ C[1];
	assign S[3] = p[3] ^ C[2];

endmodule

module cla_16b (
	input logic CI,
	input logic [15:0] A, B,
	output logic CO,
	output logic [15:0] S
);
	logic [2:0] C;
	logic [3:0] P, G;
	logic [15:0] p, g;

	// Compute the p's and g's
	com_pg pg (.A(A), .B(B), .p(p), .g(g));

	// Compute P's
	assign P[0] = &p[3:0];
	assign P[1] = &p[7:4];
	assign P[2] = &p[11:8];
	assign P[3] = &p[15:12];

	// Compute G's
	assign G[0] = g[3] | (p[3] & g[2]) | (&p[3:2] & g[1]) | (&p[3:1] & g[0]);
	assign G[1] = g[7] | (p[7] & g[6]) | (&p[7:6] & g[5]) | (&p[7:5] & g[4]);
	assign G[2] = g[11] | (p[11] & g[10]) | (&p[11:10] & g[9]) | (&p[11:9] & g[8]);
	assign G[3] = g[15] | (p[15] & g[14]) | (&p[15:14] & g[13]) | (&p[15:13] & g[12]);

	// Compute the carries
	assign C[0] = G[0] | (P[0] & CI);
	assign C[1] = G[1] | (P[1] & G[0]) | (&P[1:0] & CI);
	assign C[2] = G[2] | (P[2] & G[1]) | (&P[2:1] & G[0]) | (&P[2:0] & CI);
	assign CO = G[3] | (P[3] & G[2]) | (&P[3:2] & G[1]) | (&P[3:1] & G[0]) | (&P[3:0] & CI);

	// Compute the sums
	cla_4b s1 (.CI(CI), .p(p[3:0]), .g(g[3:0]), .S(S[3:0]));
	cla_4b s2 (.CI(C[0]), .p(p[7:4]), .g(g[7:4]), .S(S[7:4]));
	cla_4b s3 (.CI(C[1]), .p(p[11:8]), .g(g[11:8]), .S(S[11:8]));
	cla_4b s4 (.CI(C[2]), .p(p[15:12]), .g(g[15:12]), .S(S[15:12]));

endmodule

cla_tb.sv
module tb ();
    logic [15:0] tb_X;
    logic [15:0] tb_Y;
    logic [15:0] tb_S;
    logic tb_CO;

    // instance of DUT
    cla_16b test (.CI(1'b0), .A(tb_X), .B(tb_Y), .CO(tb_CO), .S(tb_S));

    initial begin
        
        $monitor ("A=%d, B=%d, CO=%d, S=%d", tb_X, tb_Y, tb_CO, tb_S);

        #1
        tb_X = 0;
        tb_Y = 0;

        #1
        tb_X = 1;
        tb_Y = 0;

        #1
        tb_X = 2;
        tb_Y = 1;

        #1
        tb_X = 2;
        tb_Y = 3;

        #1
        tb_X = 3;
        tb_Y = 3;

        #1
        tb_X = 7;
        tb_Y = 3;

        #1
        tb_X = 3;
        tb_Y = 12;

        #1
        tb_X = 10;
        tb_Y = 0;
        
        #1
        tb_X = 3;
        tb_Y = 4;

        #1
        tb_X = 14;
        tb_Y = 1;

        #1
        tb_X = 3;
        tb_Y = 6;

        #1
        tb_X = 7;
        tb_Y = 2;

        #1
        tb_X = 1;
        tb_Y = 5;

        #1
        tb_X = 6;
        tb_Y = 4;

        #1
        tb_X = 15;
        tb_Y = 15;

        #1
        $display("TEST COMPLETE");
        $finish();
    end

    // To dump signals to waveform
    initial begin
        $dumpfile("dump.vcd");
        $dumpvars; 
    end

endmodule

dump.vcd
$date
	Tue Dec 27 15:27:32 2022
$end
$version
	Icarus Verilog
$end
$timescale
	1s
$end
$scope module tb $end
$var wire 16 ! tb_S [15:0] $end
$var wire 1 " tb_CO $end
$var reg 16 # tb_X [15:0] $end
$var reg 16 $ tb_Y [15:0] $end
$scope module test $end
$var wire 16 % A [15:0] $end
$var wire 16 & B [15:0] $end
$var wire 1 ' CI $end
$var wire 1 " CO $end
$var wire 16 ( p [15:0] $end
$var wire 16 ) g [15:0] $end
$var wire 16 * S [15:0] $end
$var wire 4 + P [3:0] $end
$var wire 4 , G [3:0] $end
$var wire 3 - C [2:0] $end
$scope module pg $end
$var wire 16 . A [15:0] $end
$var wire 16 / B [15:0] $end
$var wire 16 0 p [15:0] $end
$var wire 16 1 g [15:0] $end
$upscope $end
$scope module s1 $end
$var wire 1 ' CI $end
$var wire 4 2 g [3:0] $end
$var wire 4 3 p [3:0] $end
$var wire 4 4 S [3:0] $end
$var wire 3 5 C [2:0] $end
$upscope $end
$scope module s2 $end
$var wire 1 6 CI $end
$var wire 4 7 g [3:0] $end
$var wire 4 8 p [3:0] $end
$var wire 4 9 S [3:0] $end
$var wire 3 : C [2:0] $end
$upscope $end
$scope module s3 $end
$var wire 1 ; CI $end
$var wire 4 < g [3:0] $end
$var wire 4 = p [3:0] $end
$var wire 4 > S [3:0] $end
$var wire 3 ? C [2:0] $end
$upscope $end
$scope module s4 $end
$var wire 1 @ CI $end
$var wire 4 A g [3:0] $end
$var wire 4 B p [3:0] $end
$var wire 4 C S [3:0] $end
$var wire 3 D C [2:0] $end
$upscope $end
$upscope $end
$upscope $end
$enddefinitions $end
#0
$dumpvars
bx D
bx C
bx B
bx A
x@
bx ?
bx >
bx =
bx <
x;
bx :
bx 9
bx 8
bx 7
x6
bx 5
bx 4
bx 3
bx 2
bx 1
bx 0
bx /
bx .
bx -
bx ,
bx +
bx *
bx )
bx (
0'
bx &
bx %
bx $
bx #
x"
bx !
$end
#1
0@
0"
0;
06
b0 9
b0 >
b0 C
b0 -
b0 :
b0 ?
b0 D
b0 !
b0 *
b0 4
b0 5
b0 ,
b0 3
b0 8
b0 =
b0 B
b0 +
b0 2
b0 7
b0 <
b0 A
b0 (
b0 0
b0 )
b0 1
b0 $
b0 &
b0 /
b0 #
b0 %
b0 .
#2
b1 !
b1 *
b1 4
b1 3
b1 (
b1 0
b1 #
b1 %
b1 .
#3
b11 !
b11 *
b11 4
b11 3
b11 (
b11 0
b1 $
b1 &
b1 /
b10 #
b10 %
b10 .
#4
b10 5
b101 !
b101 *
b101 4
b1 3
b10 2
b1 (
b1 0
b10 )
b10 1
b11 $
b11 &
b11 /
#5
b110 !
b110 *
b110 4
b11 5
b0 3
b11 2
b0 (
b0 0
b11 )
b11 1
b11 #
b11 %
b11 .
#6
b111 5
b1010 !
b1010 *
b1010 4
b100 3
b100 (
b100 0
b111 #
b111 %
b111 .
#7
b1111 !
b1111 *
b1111 4
b0 5
b1111 3
b1 +
b0 2
b1111 (
b1111 0
b0 )
b0 1
b1100 $
b1100 &
b1100 /
b11 #
b11 %
b11 .
#8
b1010 !
b1010 *
b1010 4
b1010 3
b0 +
b1010 (
b1010 0
b0 $
b0 &
b0 /
b1010 #
b1010 %
b1010 .
#9
b111 !
b111 *
b111 4
b111 3
b111 (
b111 0
b100 $
b100 &
b100 /
b11 #
b11 %
b11 .
#10
b1111 !
b1111 *
b1111 4
b1111 3
b1 +
b1111 (
b1111 0
b1 $
b1 &
b1 /
b1110 #
b1110 %
b1110 .
#11
b110 5
b1001 !
b1001 *
b1001 4
b10 2
b101 3
b0 +
b10 )
b10 1
b101 (
b101 0
b110 $
b110 &
b110 /
b11 #
b11 %
b11 .
#12
b10 $
b10 &
b10 /
b111 #
b111 %
b111 .
#13
b110 !
b110 *
b110 4
b1 5
b100 3
b1 2
b100 (
b100 0
b1 )
b1 1
b101 $
b101 &
b101 /
b1 #
b1 %
b1 .
#14
b1010 !
b1010 *
b1010 4
b100 5
b10 3
b100 2
b10 (
b10 0
b100 )
b100 1
b100 $
b100 &
b100 /
b110 #
b110 %
b110 .
#15
b1 9
16
b1 -
b1 ,
b11110 !
b11110 *
b1110 4
b111 5
b0 3
b1111 2
b0 (
b0 0
b1111 )
b1111 1
b1111 $
b1111 &
b1111 /
b1111 #
b1111 %
b1111 .
